{
  "experiment_name": "xgb_default_all_smote",
  "model_type": "xgboost",
  "model_params": {
    "n_estimators": 200,
    "learning_rate": 0.05,
    "max_depth": 7,
    "min_child_weight": 3,
    "subsample": 0.8,
    "colsample_bytree": 0.8,
    "gamma": 0.1
  },
  "feature_subset": "all",
  "n_features": 288,
  "use_smote": true,
  "class_weight": 1.5009628654876914,
  "training_time_sec": 5.776180982589722,
  "metrics": {
    "ROC_AUC": 0.7521,
    "PR_AUC": 0.1874,
    "F2_score": 0.3829,
    "best_threshold": 0.12,
    "n_samples": 25089,
    "n_positive": 1706
  }
}